newsscrapper/__init__.py
newsscrapper/en.py
newsscrapper/es.py
newsscrapper/fr.py
newsscrapper/utils.py
newsscrapper_SamirPS-1.0.5.dist-info/METADATA
newsscrapper_SamirPS-1.0.5.dist-info/WHEEL
newsscrapper_SamirPS-1.0.5.dist-info/top_level.txt
newsscrapper_SamirPS-1.0.5.dist-info/RECORD
