Metadata-Version: 2.1
Name: newsscrapper-SamirPS
Version: 1.0.5
Home-page: https://github.com/SamirPS/News-Scrapper
Author: SamirPS
License: MIT
Classifier: Programming Language :: Python :: 3
Classifier: License :: OSI Approved :: MIT License
Classifier: Operating System :: OS Independent
Requires-Python: >=3.6
Requires-Dist: requests
Requires-Dist: bs4
Requires-Dist: lxml
Requires-Dist: newspaper3k
